webhook_client/__init__.py
webhook_client/client.py
webhook_client/colour.py
webhook_client/embed.py
webhook_client/errors.py
webhook_client/types.py
webhook_client-1.0.2.dist-info/LICENSE
webhook_client-1.0.2.dist-info/METADATA
webhook_client-1.0.2.dist-info/WHEEL
webhook_client-1.0.2.dist-info/top_level.txt
webhook_client-1.0.2.dist-info/RECORD
