Metadata-Version: 2.1
Name: webhook-client
Version: 1.0.2
Summary: A discord webhook client written in Python.
Home-page: https://github.com/ElijahGives/discord-webhook
Author: ElijahGives
Author-email: elijahgives13@gmail.com
License: LICENSE
Platform: UNKNOWN
Classifier: Programming Language :: Python :: 3
Classifier: License :: OSI Approved :: GNU General Public License v3 or later (GPLv3+)
Classifier: Operating System :: OS Independent
License-File: LICENSE
